etched_sphinx_theme/__init__.py
etched_sphinx_theme/layout.html
etched_sphinx_theme/theme.conf
etched_sphinx_theme/static/logo.svg
etched_sphinx_theme/static/theme.css
etched_sphinx_theme/static/tw_input.css
etched_sphinx_theme/static/tw_output.css
etched_sphinx_theme/static/fonts/TT Interphases Pro Mono Variable.ttf
etched_sphinx_theme/static/fonts/TT Interphases Pro Variable.ttf
etched_sphinx_theme/static/images/colab.svg
etched_sphinx_theme/static/images/download.svg
etched_sphinx_theme/static/images/github.svg
etched_sphinx_theme/static/js/notebook-cells.js
etched_sphinx_theme/static/js/toc-highlight.js
etched_sphinx_theme-0.1.1.dist-info/METADATA
etched_sphinx_theme-0.1.1.dist-info/WHEEL
etched_sphinx_theme-0.1.1.dist-info/entry_points.txt
etched_sphinx_theme-0.1.1.dist-info/top_level.txt
etched_sphinx_theme-0.1.1.dist-info/RECORD
