Metadata-Version: 2.1
Name: etched-sphinx-theme
Version: 0.1.1
Summary: Etched sphinx theme
Author-email: Colin Zhao <colin@etched.com>
License: MIT
Keywords: sphinx,theme,documentation
Classifier: Framework :: Sphinx
Classifier: Framework :: Sphinx :: Theme
Classifier: Development Status :: 3 - Alpha
Classifier: License :: OSI Approved :: MIT License
Classifier: Programming Language :: Python :: 3
Classifier: Programming Language :: Python :: 3.7
Classifier: Programming Language :: Python :: 3.8
Classifier: Programming Language :: Python :: 3.9
Classifier: Programming Language :: Python :: 3.10
Classifier: Operating System :: OS Independent
Requires-Dist: sphinx==6.0.0
Requires-Dist: myst-nb==1.1.0
